LatexToCNF/__init__.py
LatexToCNF/__main__.py
LatexToCNF/cnf_builder.py
LatexToCNF/formula_validetor.py
LatexToCNF/latex_parser.py
LatexToCNF/run.py
LatexToCNF-0.1.4.dist-info/LICENSE
LatexToCNF-0.1.4.dist-info/METADATA
LatexToCNF-0.1.4.dist-info/WHEEL
LatexToCNF-0.1.4.dist-info/entry_points.txt
LatexToCNF-0.1.4.dist-info/top_level.txt
LatexToCNF-0.1.4.dist-info/RECORD
