Metadata-Version: 2.1
Name: LatexToCNF
Version: 0.1.4
Summary: python cli program to convert latex input to CNF (conjunctive normal form).
Home-page: https://github.com/Azgmohammadd/LatexToCNF
Author: azgmohammadd
Author-email: azgmohammadd@gmail.com
License: MIT
Platform: UNKNOWN
Classifier: License :: OSI Approved :: MIT License
Classifier: Programming Language :: Python :: 3
Requires-Python: >=3.8
License-File: LICENSE
Requires-Dist: pyparsing (==2.4.7)
